sema4ai/data/__init__.py
sema4ai/data/_config.py
sema4ai/data/_connection_provider.py
sema4ai/data/_data_server_connection.py
sema4ai/data/_data_source.py
sema4ai/data/_data_source_spec.py
sema4ai/data/_models.py
sema4ai/data/_result_set.py
sema4ai/data/_snowflake.py
sema4ai/data/_sql_handling.py
sema4ai/data/py.typed
sema4ai_data-1.2.2.dist-info/LICENSE
sema4ai_data-1.2.2.dist-info/METADATA
sema4ai_data-1.2.2.dist-info/WHEEL
sema4ai_data-1.2.2.dist-info/RECORD
