Metadata-Version: 2.3
Name: sema4ai-data
Version: 1.2.2
Summary: Sema4.ai Data
License: Sema4.ai Proprietary (see LICENSE)
Author: Sema4.ai
Author-email: dev@sema4.ai
Requires-Python: >=3.10,<4.0
Classifier: License :: Other/Proprietary License
Classifier: Programming Language :: Python :: 3
Classifier: Programming Language :: Python :: 3.10
Classifier: Programming Language :: Python :: 3.11
Classifier: Programming Language :: Python :: 3.12
Classifier: Programming Language :: Python :: 3.13
Requires-Dist: pandas (>=1.3.5)
Requires-Dist: sema4ai-actions (>=1.3.8,<2.0.0)
Requires-Dist: snowflake-connector-python[pandas] (>=3.15.0)
Project-URL: Repository, https://github.com/Sema4AI/data/
